README.rst
setup.py
sm/__init__.py
sm/splitmedia.py
sm/resources/scripts/splitmedia
splitmedia.egg-info/PKG-INFO
splitmedia.egg-info/SOURCES.txt
splitmedia.egg-info/dependency_links.txt
splitmedia.egg-info/not-zip-safe
splitmedia.egg-info/top_level.txt