Metadata-Version: 1.0
Name: splitmedia
Version: 0.2.1
Summary: Split one media file into many based on a list of offsets
Home-page: https://github.com/dsoprea/splitmedia
Author: Dustin Oprea
Author-email: myselfasunder@gmail.com
License: GPL 2
Keywords: split audio video
Platform: UNKNOWN
